bimms/__init__.py
bimms/_misc/calibrations/test.json
bimms/_misc/configs/test.json
bimms/backend/BIMMS_Class.py
bimms/backend/file_handler.py
bimms/calibration/__init__.py
bimms/calibration/calibration.py
bimms/measure/Measure.py
bimms/measure/__init__.py
bimms/results/Results.py
bimms/system/BIMMS.py
bimms/system/BIMMSad2.py
bimms/system/BIMMScalibration.py
bimms/system/BIMMSconfig.py
bimms/system/BIMMShardware.py
bimms/system/__init__.py
bimms/utils/PostProcessing.py
bimms/utils/__init__.py
bimms/utils/config_mode.py
bimms/utils/constants.py
bimms/utils/functions.py
bimms-1.1.3.dist-info/METADATA
bimms-1.1.3.dist-info/WHEEL
bimms-1.1.3.dist-info/top_level.txt
bimms-1.1.3.dist-info/RECORD
